kvell_extraction/__init__.py
kvell_extraction/main.py
kvell_extraction/utils.py
kvell_extraction-0.0.6.dist-info/METADATA
kvell_extraction-0.0.6.dist-info/WHEEL
kvell_extraction-0.0.6.dist-info/entry_points.txt
kvell_extraction-0.0.6.dist-info/top_level.txt
kvell_extraction-0.0.6.dist-info/RECORD
