Metadata-Version: 2.2
Name: kvell-extraction
Version: 0.0.6
Summary: A comprehensive text extraction tool supporting multiple file formats
Author: KvelKrishna
Project-URL: Homepage, https://github.com/yourusername/kvell-extraction
Platform: Any
Classifier: Programming Language :: Python :: 3
Classifier: License :: OSI Approved :: MIT License
Classifier: Operating System :: OS Independent
Requires-Python: >=3.7
Requires-Dist: PyMuPDF
Requires-Dist: filetype
Requires-Dist: rapidocr_onnxruntime
Requires-Dist: spire.doc
Requires-Dist: polars
Requires-Dist: fastexcel
Requires-Dist: python-pptx
Requires-Dist: opencv-python
Requires-Dist: numpy
Provides-Extra: onnxruntime
Requires-Dist: rapidocr_onnxruntime; extra == "onnxruntime"
Dynamic: platform
